pretix_checkinlist_net/__init__.py
pretix_checkinlist_net/apps.py
pretix_checkinlist_net/exporters.py
pretix_checkinlist_net/signals.py
pretix_checkinlist_net/locale/de/LC_MESSAGES/django.po
pretix_checkinlist_net/locale/de_Informal/.gitkeep
pretix_checkinlist_net/locale/de_Informal/LC_MESSAGES/django.po
pretix_checkinlist_net/static/pretix_checkinlist_net/.gitkeep
pretix_checkinlist_net/templates/pretix_checkinlist_net/.gitkeep
pretix_checkinlist_net-2.0.6.dist-info/AUTHORS
pretix_checkinlist_net-2.0.6.dist-info/LICENSE
pretix_checkinlist_net-2.0.6.dist-info/METADATA
pretix_checkinlist_net-2.0.6.dist-info/WHEEL
pretix_checkinlist_net-2.0.6.dist-info/entry_points.txt
pretix_checkinlist_net-2.0.6.dist-info/top_level.txt
pretix_checkinlist_net-2.0.6.dist-info/RECORD
