Metadata-Version: 2.1
Name: pretix-checkinlist-net
Version: 2.0.6
Summary: Pretix checkin list exporter for NETWAYS
Home-page: https://github.com/NETWAYS/pretix-checkinlist-net
Download-URL: https://github.com/NETWAYS/pretix-invoice-net/archive/v2.0.5.tar.gz
Author: NETWAYS GmbH
Author-email: support@netways.de
License: Apache Software License
Keywords: pretix,tickets,events,invoice,pdf
License-File: LICENSE
License-File: AUTHORS
Requires-Dist: packaging
